AGSecurityPostgres/__init__.py
AGSecurityPostgres/security_create.py
AGSecurityPostgres/security_list.py
AGSecurityPostgres/security_update.py
AGSecurityPostgres-1.0.10.dist-info/LICENSE
AGSecurityPostgres-1.0.10.dist-info/METADATA
AGSecurityPostgres-1.0.10.dist-info/WHEEL
AGSecurityPostgres-1.0.10.dist-info/top_level.txt
AGSecurityPostgres-1.0.10.dist-info/RECORD
