Metadata-Version: 2.1
Name: AGSecurityPostgres
Version: 1.0.10
Summary: Security Query Builder
Author-email: Michael Lundager <michael@wivvies.com>
License: MIT License        
Classifier: Programming Language :: Python :: 3
Classifier: License :: OSI Approved :: MIT License
Classifier: Operating System :: OS Independent
Requires-Python: >=3.7
License-File: LICENSE
Requires-Dist: AGCoder
Requires-Dist: AGQueryPostgres
Requires-Dist: psycopg2-binary
